{
  "menu": [
    {
      "img": "img/tabs/vegy.jpg",
      "altimg": "vegy",
      "title": "Меню 'Фитнес'",
      "descr": "Меню 'Фитнес' - это новый подход к приготовлению блюд: больше свежих овощей и фруктов. Продукт активных и здоровых людей. Это абсолютно новый продукт с оптимальной ценой и высоким качеством!",
      "price": 9,
      "id": "4c86"
    },
    {
      "img": "img/tabs/post.jpg",
      "altimg": "post",
      "title": "Меню 'Постное'",
      "descr": "Меню 'Постное' - это тщательный подбор ингредиентов: полное отсутствие продуктов животного происхождения, молоко из миндаля, овса, кокоса или гречки, правильное количество белков за счет тофу и импортных вегетарианских стейков.",
      "price": 14,
      "id": "b60c"
    },
    {
      "img": "img/tabs/elite.jpg",
      "altimg": "elite",
      "title": "Меню 'Премиум'",
      "descr": "В меню 'Премиум' мы используем не только красивый дизайн упаковки, но и качественное исполнение блюд. Красная рыба, морепродукты, фрукты - ресторанное меню без похода в ресторан!",
      "price": 21,
      "id": "c8c4"
    }
  ],
  "requests": [
    {
      "id": "b8f2",
      "name": "Софія",
      "phone": "+38 (956) 286-63-35"
    },
    {
      "id": "f684",
      "name": "Aлиса",
      "phone": "+380 60 564 63 63"
    }
  ]
}